<?xml version="1.0" encoding="utf-8" ?><dwsync><file name="class.upload.ca_CA.php" local="-3759799415842275328" remote="-3255764547801216632" testing="0" /><file name="class.upload.cs_CS.php" local="-3759799415842275328" remote="-3255764547801216632" testing="0" /><file name="class.upload.de_DE.php" local="-3759799415842275328" remote="-3255764547801216632" testing="0" /><file name="class.upload.el_GR.php" local="-3759799415842275328" remote="-3255764547801216632" testing="0" /><file name="class.upload.es_ES.php" local="-3759799415842275328" remote="-3255764547801216632" testing="0" /><file name="class.upload.et_EE.php" local="-3759799415842275328" remote="-3255764547801216632" testing="0" /><file name="class.upload.fr_FR.php" local="-3759799415842275328" remote="-3255764547801216632" testing="0" /><file name="class.upload.he_IL.php" local="-3759799415842275328" remote="-3255764547801216632" testing="0" /><file name="class.upload.hr_HR.php" local="-3759799415842275328" remote="-3255764547801216632" testing="0" /><file name="class.upload.id_ID.php" local="-3759799415842275328" remote="-3255764547801216632" testing="0" /><file name="class.upload.it_IT.php" local="-3759799415842275328" remote="-3255764547801216632" testing="0" /><file name="class.upload.lt_LT.php" local="-3759799415842275328" remote="-3255764547801216632" testing="0" /><file name="class.upload.nl_NL.php" local="-3759799415842275328" remote="-3255764547801216632" testing="0" /><file name="class.upload.no_NO.php" local="-3759799415842275328" remote="-3255764547801216632" testing="0" /><file name="class.upload.pl_PL.php" local="-3759799415842275328" remote="-3255764547801216632" testing="0" /><file name="class.upload.pt_BR.php" local="-3759799415842275328" remote="-3255764547801216632" testing="0" /><file name="class.upload.ro_RO.php" local="-3759799415842275328" remote="-3255764547801216632" testing="0" /><file name="class.upload.ru_RU.php" local="-3759799415842275328" remote="-3255764547801216632" testing="0" /><file name="class.upload.ru_RU.windows-1251.php" local="-3759799415842275328" remote="-3255764547801216632" testing="0" /><file name="class.upload.sk_SK.php" local="-3759799415842275328" remote="-3255764547801216632" testing="0" /><file name="class.upload.sv_SE.php" local="-3759799415842275328" remote="-3255764547801216632" testing="0" /><file name="class.upload.tr_TR.php" local="-3759799415842275328" remote="-3255764547801216632" testing="0" /><file name="class.upload.uk_UA.php" local="-3759799415842275328" remote="-3255764547801216632" testing="0" /><file name="class.upload.uk_UA.windows-1251.php" local="-3759799415842275328" remote="-3255764547801216632" testing="0" /><file name="class.upload.vn_VN.php" local="-3759799415842275328" remote="-3255764547801216632" testing="0" /><file name="class.upload.xx_XX.php" local="-3759799415842275328" remote="-3255764547801216632" testing="0" /><file name="class.upload.zh_CN.gb-2312.php" local="-3759799415842275328" remote="-3255764547801216632" testing="0" /><file name="class.upload.zh_CN.php" local="-3759799415842275328" remote="-3255764547801216632" testing="0" /><file name="class.upload.zh_TW.php" local="-3759799407252340736" remote="-3255764547801216632" testing="0" /></dwsync>